iohandler/IOBridge.py
iohandler/IOFile.py
iohandler/__init__.py
iohandler-1.0.6.dist-info/METADATA
iohandler-1.0.6.dist-info/RECORD
iohandler-1.0.6.dist-info/WHEEL
iohandler-1.0.6.dist-info/top_level.txt
